pygoerrors/__init__.py
pygoerrors/decorators.py
pygoerrors/errors.py
pygoerrors/format.py
pygoerrors/helpers.py
pygoerrors/iterators.py
pygoerrors/protocols.py
pygoerrors/py.typed
pygoerrors-0.2.0.dist-info/LICENSE
pygoerrors-0.2.0.dist-info/METADATA
pygoerrors-0.2.0.dist-info/WHEEL
pygoerrors-0.2.0.dist-info/RECORD
