Metadata-Version: 2.3
Name: pygoerrors
Version: 0.2.0
Summary: Go like errors for Python
License: GNU GENERAL PUBLIC LICENSE
Keywords: error,errors,go,exceptions,error-handling,go-style,exceptions,error-wrapping,python-errors,error-protocol,functional-programming
Author: dreadster3
Author-email: afonso.antunes@live.com.pt
Requires-Python: >=3.12
Classifier: Development Status :: 4 - Beta
Classifier: Operating System :: MacOS
Classifier: Operating System :: Microsoft :: Windows
Classifier: Operating System :: POSIX
Classifier: Topic :: Software Development :: Libraries :: Python Modules
Classifier: Intended Audience :: Developers
Classifier: License :: OSI Approved :: GNU Affero General Public License v3
Classifier: Programming Language :: Python
Classifier: Programming Language :: Python :: 3.12
Classifier: Programming Language :: Python :: 3.13
Requires-Dist: cachetools (>=6.0.0,<7.0.0)
Project-URL: Source, https://github.com/dreadster3/pygoerrors
Project-URL: Tracker, https://github.com/dreadster3/pygoerrors/issues
